barbq/__init__.py
barbq/query.py
barbq-0.0.3.dist-info/LICENSE
barbq-0.0.3.dist-info/METADATA
barbq-0.0.3.dist-info/WHEEL
barbq-0.0.3.dist-info/top_level.txt
barbq-0.0.3.dist-info/RECORD
