Metadata-Version: 2.1
Name: barbq
Version: 0.0.3
Summary: Python-native SQL dialect that renders to BigQuery
Home-page: https://github.com/faradayio/barbq
Author: Kirby Gordon
Author-email: kirby.gordon@faraday.io
License: UNKNOWN
Platform: UNKNOWN
Classifier: Programming Language :: Python :: 3
Classifier: License :: OSI Approved :: MIT License
Classifier: Operating System :: OS Independent
Requires-Python: >=3.6
License-File: LICENSE
